{"cameraMode":{"drawMode":0,"name":"Shaded","section":"Shading Mode"},"sceneLighting":false,"audioPlay":false,"sceneViewState":{"showFog":true,"showMaterialUpdate":false,"showSkybox":false,"showFlares":true,"showImageEffects":true,"showParticleSystems":true},"in2DMode":false,"pivot":{"x":23.140064239501954,"y":5.913143634796143,"z":0.6064886450767517},"rotation":{"x":-0.017652766779065133,"y":-0.6030859351158142,"z":-0.013444289565086365,"w":0.797398567199707},"size":0.8949999809265137,"orthographic":false}